Verilog_Implementation/Implementation_of_15_7_MLD/Type_I_MLD/mux_2_1.v
module mux_2_1(in0, in1, out, sel);
	input in0, in1, sel;
	output reg out;

	always @(*) begin
		if (sel)
			out = in1;
		else
			out = in0;
	end
endmodule

Verilog_Implementation/Implementation_of_7_4_MLD/Type_I_MLD/d_flip_flop.v
module d_flip_flop(reset, clk, D, Q);
	input reset, clk, D;
	output reg Q;

	always @(posedge clk) begin
		if (reset)
			Q <= 0;
		else
			Q <= D;
	end
endmodule

Verilog_Implementation/Implementation_of_15_7_MLD/Type_I_MLD/MLD_15_7_encoder.v
module MLD_15_7_encoder(clk, reset, out, information_bit, sel);
	input clk, reset, information_bit, sel;
	output out;
	reg ff1_input, ff2_input, ff3_input, ff4_input, ff5_input, ff6_input, ff7_input, ff8_input;
	wire ff1_output, ff2_output, ff3_output, ff4_output, ff5_output, ff6_output, ff7_output, ff8_output;
	wire gate_input, gate_output;
	wire final_flip_flop_output_after_delay;

	assign gate_input = ff8_output ^ information_bit;	

	d_flip_flop FF1(reset, clk, ff1_input, ff1_output);
	d_flip_flop FF2(reset, clk, ff2_input, ff2_output);
	d_flip_flop FF3(reset, clk, ff3_input, ff3_output);
	d_flip_flop FF4(reset, clk, ff4_input, ff4_output);
	d_flip_flop FF5(reset, clk, ff5_input, ff5_output);
	d_flip_flop FF6(reset, clk, ff6_input, ff6_output);
	d_flip_flop FF7(reset, clk, ff7_input, ff7_output);
	d_flip_flop FF8(reset, clk, ff8_input, ff8_output);
	mux_2_1 SWITCH(information_bit, final_flip_flop_output_after_delay, out, sel);
	mux_2_1 GATE(gate_input, 1'b0, gate_output, sel);
	buf #2 G1(final_flip_flop_output_after_delay, ff8_output);

	always @(*) begin
		ff1_input = gate_output;
		ff2_input = ff1_output;
		ff3_input = ff2_output;
		ff4_input = ff3_output;
		ff5_input = ff4_output ^ gate_output;
		ff6_input = ff5_output;
		ff7_input = ff6_output ^ gate_output;
		ff8_input = ff7_output ^ gate_output;
	end
endmodule

Verilog_Implementation/Implementation_of_15_7_MLD/Type_II_MLD/MLD_15_7_encoder_test_bench.v
module MLD_15_7_Encoder_test_bench;
	reg reset, clk, information_bit, sel;
	wire out;

	MLD_15_7_encoder DUT(clk, reset, out, information_bit, sel);

	initial clk = 0;
	always #5 clk = ~clk;

	initial begin
		$dumpfile("MLD_15_7_encoder.vcd");
		$dumpvars(0, MLD_15_7_Encoder_test_bench);
		$monitor($time, ": Bit sent into Channel: %b", out);
		information_bit = 1'b0;
		reset = 1'b1;
		#7 reset = 1'b0;
		information_bit = 1'b1;
		#10 information_bit = 1'b0;
		#10 information_bit = 1'b0;
		#10 information_bit = 1'b0;
		#10 information_bit = 1'b0;
		#10 information_bit = 1'b0;
		#10 information_bit = 1'b0;
		#10 sel = 1'b1;
		information_bit = 1'b0;
		#80 $finish;
	end
endmodule

Verilog_Implementation/Implementation_of_15_7_MLD/Type_I_MLD/MLD_15_7_encoder.vcd
$date
	Wed Jan 25 00:28:00 2023
$end
$version
	Icarus Verilog
$end
$timescale
	1s
$end
$scope module MLD_15_7_Encoder_test_bench $end
$var wire 1 ! out $end
$var reg 1 " clk $end
$var reg 1 # information_bit $end
$var reg 1 $ reset $end
$var reg 1 % sel $end
$scope module DUT $end
$var wire 1 " clk $end
$var wire 1 & final_flip_flop_output_after_delay $end
$var wire 1 ' gate_input $end
$var wire 1 # information_bit $end
$var wire 1 $ reset $end
$var wire 1 % sel $end
$var wire 1 ! out $end
$var wire 1 ( gate_output $end
$var wire 1 ) ff8_output $end
$var wire 1 * ff7_output $end
$var wire 1 + ff6_output $end
$var wire 1 , ff5_output $end
$var wire 1 - ff4_output $end
$var wire 1 . ff3_output $end
$var wire 1 / ff2_output $end
$var wire 1 0 ff1_output $end
$var reg 1 1 ff1_input $end
$var reg 1 2 ff2_input $end
$var reg 1 3 ff3_input $end
$var reg 1 4 ff4_input $end
$var reg 1 5 ff5_input $end
$var reg 1 6 ff6_input $end
$var reg 1 7 ff7_input $end
$var reg 1 8 ff8_input $end
$scope module FF1 $end
$var wire 1 1 D $end
$var wire 1 " clk $end
$var wire 1 $ reset $end
$var reg 1 0 Q $end
$upscope $end
$scope module FF2 $end
$var wire 1 2 D $end
$var wire 1 " clk $end
$var wire 1 $ reset $end
$var reg 1 / Q $end
$upscope $end
$scope module FF3 $end
$var wire 1 3 D $end
$var wire 1 " clk $end
$var wire 1 $ reset $end
$var reg 1 . Q $end
$upscope $end
$scope module FF4 $end
$var wire 1 4 D $end
$var wire 1 " clk $end
$var wire 1 $ reset $end
$var reg 1 - Q $end
$upscope $end
$scope module FF5 $end
$var wire 1 5 D $end
$var wire 1 " clk $end
$var wire 1 $ reset $end
$var reg 1 , Q $end
$upscope $end
$scope module FF6 $end
$var wire 1 6 D $end
$var wire 1 " clk $end
$var wire 1 $ reset $end
$var reg 1 + Q $end
$upscope $end
$scope module FF7 $end
$var wire 1 7 D $end
$var wire 1 " clk $end
$var wire 1 $ reset $end
$var reg 1 * Q $end
$upscope $end
$scope module FF8 $end
$var wire 1 8 D $end
$var wire 1 " clk $end
$var wire 1 $ reset $end
$var reg 1 ) Q $end
$upscope $end
$scope module GATE $end
$var wire 1 ' in0 $end
$var wire 1 9 in1 $end
$var wire 1 % sel $end
$var reg 1 ( out $end
$upscope $end
$scope module SWITCH $end
$var wire 1 # in0 $end
$var wire 1 & in1 $end
$var wire 1 % sel $end
$var reg 1 ! out $end
$upscope $end
$upscope $end
$upscope $end
$enddefinitions $end
#0
$dumpvars
09
x8
x7
x6
x5
x4
x3
x2
x1
x0
x/
x.
x-
x,
x+
x*
x)
x(
x'
x&
x%
1$
0#
0"
0!
$end
#5
08
07
05
01
0(
06
04
03
02
0'
00
0/
0.
0-
0,
0+
0*
0)
1"
#7
18
17
15
11
1(
1'
1!
0&
1#
0$
#10
0"
#15
07
05
01
0(
0'
18
16
12
1)
1*
1,
10
1"
#17
08
17
15
11
1(
1'
0!
1&
0#
#20
0"
#25
18
05
01
0(
17
13
0'
1/
1+
0)
1"
#27
0&
#30
0"
#35
08
07
15
11
1(
1'
06
14
02
1)
0,
1.
00
1"
#37
1&
#40
0"
#45
01
0(
08
07
16
15
03
12
0'
10
0/
1-
1,
0+
0*
0)
1"
#47
0&
#50
0"
#55
17
04
13
02
1+
0.
1/
00
1"
#60
0"
#65
18
05
14
03
0/
1.
0-
1*
1"
#70
0"
#75
08
07
11
1(
1'
06
05
04
1)
0,
1-
0.
1"
#77
18
17
15
01
0(
1!
1&
1%
#80
0"
#85
07
16
05
0-
1,
0+
1"
#90
0"
#95
08
17
06
0*
1+
0,
1"
#100
0"
#105
18
07
0'
0+
1*
0)
1"
#107
0!
0&
#110
0"
#115
1'
08
1)
0*
1"
#117
1!
1&
#120
0"
#125
0'
0)
1"
#127
0!
0&
