Verilog_Implementation/majority_gate_3_input.v
module majority_gate_3_input(M, A, B, C);
	input A, B, C;
	output M;
	wire t0, t1, t2;

	and G1(t0, A, B);
	and G2(t1, B, C);
	and G3(t2, A, C);
	or G4(M, t0, t1, t2);
endmodule

Verilog_Implementation/Implementation_of_7_4_MLD/Type_I_MLD/d_flip_flop.v
module d_flip_flop(reset, clk, D, Q);
	input reset, clk, D;
	output reg Q;

	always @(posedge clk) begin
		if (reset)
			Q <= 0;
		else
			Q <= D;
	end
endmodule

Verilog_Implementation/Implementation_of_7_4_MLD/Type_II_MLD/MLD_7_4_decoder.v
module MLD_7_4_decoder(clk, reset, load, received_bit_stream, decoded_vector);
	input clk, reset, load;
	input received_bit_stream;
	output[0:6] decoded_vector;
	reg w0;
	reg parity_check_sum_1, parity_check_sum_2, parity_check_sum_3;
	wire error_value;

	d_flip_flop FF1(reset, clk, w0, decoded_vector[0]);
	d_flip_flop FF2(reset, clk, decoded_vector[0], decoded_vector[1]);
	d_flip_flop FF3(reset, clk, decoded_vector[1], decoded_vector[2]);
	d_flip_flop FF4(reset, clk, decoded_vector[2], decoded_vector[3]);
	d_flip_flop FF5(reset, clk, decoded_vector[3], decoded_vector[4]);
	d_flip_flop FF6(reset, clk, decoded_vector[4], decoded_vector[5]);
	d_flip_flop FF7(reset, clk, decoded_vector[5], decoded_vector[6]);
	majority_gate_3_input M(error_value, parity_check_sum_1, parity_check_sum_2, parity_check_sum_3);

	always @(*) begin
		if (load) begin
			w0 = received_bit_stream;
		end
		else begin
			w0 = decoded_vector[6] ^ error_value;
		end
		parity_check_sum_1 = decoded_vector[3] ^ decoded_vector[4] ^ decoded_vector[6];
		parity_check_sum_2 = decoded_vector[1] ^ decoded_vector[5] ^ decoded_vector[6];
		parity_check_sum_3 = decoded_vector[0] ^ decoded_vector[2] ^ decoded_vector[6];
	end
endmodule

Verilog_Implementation/Implementation_of_7_4_MLD/Type_II_MLD/MLD_7_4_decoder_test_bench.v
module MLD_7_4_decoder_test_bench;
	reg clk, reset, load;
	reg received_bit_stream;
	wire[0:6] decoded_vector;
	
	MLD_7_4_decoder DUT(clk, reset, load, received_bit_stream, decoded_vector);

	initial clk = 1'b0;
	always #5 clk = ~clk;

	initial begin
		$dumpfile("MLD_7_4_decoder.vcd");
		$dumpvars(0, MLD_7_4_decoder_test_bench);
		$monitor("Decoded Vector: %b %b %b %b %b %b %b, Error Value: %b", decoded_vector[0], decoded_vector[1], decoded_vector[2], decoded_vector[3], decoded_vector[4], decoded_vector[5], decoded_vector[6], DUT.error_value);
		#2 load = 1'b1;
		received_bit_stream = 1'b0;
		#10 received_bit_stream = 1'b1;
		#10 received_bit_stream = 1'b1;
		#10 received_bit_stream = 1'b1;
		#10 received_bit_stream = 1'b1;
		#10 received_bit_stream = 1'b1;
		#10 received_bit_stream = 1'b0;
		#10 load = 1'b0;
		#68 $finish;
	end	
endmodule

Verilog_Implementation/Implementation_of_7_4_MLD/Type_II_MLD/MLD_7_4_decoder.vcd
$date
	Fri Jan 27 18:38:24 2023
$end
$version
	Icarus Verilog
$end
$timescale
	1s
$end
$scope module MLD_7_4_decoder_test_bench $end
$var wire 7 ! decoded_vector [0:6] $end
$var reg 1 " clk $end
$var reg 1 # load $end
$var reg 1 $ received_bit_stream $end
$var reg 1 % reset $end
$scope module DUT $end
$var wire 1 " clk $end
$var wire 1 # load $end
$var wire 1 $ received_bit_stream $end
$var wire 1 % reset $end
$var wire 1 & error_value $end
$var wire 7 ' decoded_vector [0:6] $end
$var reg 1 ( parity_check_sum_1 $end
$var reg 1 ) parity_check_sum_2 $end
$var reg 1 * parity_check_sum_3 $end
$var reg 1 + w0 $end
$scope module FF1 $end
$var wire 1 + D $end
$var wire 1 " clk $end
$var wire 1 % reset $end
$var reg 1 , Q $end
$upscope $end
$scope module FF2 $end
$var wire 1 - D $end
$var wire 1 " clk $end
$var wire 1 % reset $end
$var reg 1 . Q $end
$upscope $end
$scope module FF3 $end
$var wire 1 / D $end
$var wire 1 " clk $end
$var wire 1 % reset $end
$var reg 1 0 Q $end
$upscope $end
$scope module FF4 $end
$var wire 1 1 D $end
$var wire 1 " clk $end
$var wire 1 % reset $end
$var reg 1 2 Q $end
$upscope $end
$scope module FF5 $end
$var wire 1 3 D $end
$var wire 1 " clk $end
$var wire 1 % reset $end
$var reg 1 4 Q $end
$upscope $end
$scope module FF6 $end
$var wire 1 5 D $end
$var wire 1 " clk $end
$var wire 1 % reset $end
$var reg 1 6 Q $end
$upscope $end
$scope module FF7 $end
$var wire 1 7 D $end
$var wire 1 " clk $end
$var wire 1 % reset $end
$var reg 1 8 Q $end
$upscope $end
$scope module M $end
$var wire 1 ( A $end
$var wire 1 ) B $end
$var wire 1 * C $end
$var wire 1 & M $end
$var wire 1 9 t0 $end
$var wire 1 : t1 $end
$var wire 1 ; t2 $end
$upscope $end
$upscope $end
$upscope $end
$enddefinitions $end
#0
$dumpvars
x;
x:
x9
x8
x7
x6
x5
x4
x3
x2
x1
x0
x/
x.
x-
x,
x+
x*
x)
x(
bx '
x&
x%
x$
x#
0"
bx !
$end
#2
0+
0$
1#
#5
0-
b0xxxxxx !
b0xxxxxx '
0,
1"
#10
0"
#12
1+
1$
#15
0/
1-
0.
b10xxxxx !
b10xxxxx '
1,
1"
#20
0"
#25
1/
01
1.
b110xxxx !
b110xxxx '
00
1"
#30
0"
#35
03
11
02
b1110xxx !
b1110xxx '
10
1"
#40
0"
#45
13
05
12
b11110xx !
b11110xx '
04
1"
#50
0"
#55
07
15
06
b111110x !
b111110x '
14
1"
#60
0"
#62
0+
0$
#65
0&
0:
09
0;
0-
17
1*
0)
0(
0,
16
b111110 !
b111110 '
08
1"
#70
0"
#72
0#
#75
0/
0*
1(
1+
18
b11111 !
b11111 '
0.
1"
#80
0"
#85
1-
01
1,
b1001111 !
b1001111 '
00
1"
#90
0"
#95
03
1/
1)
0(
02
b1100111 !
b1100111 '
1.
1"
#100
0"
#105
0+
1&
1:
19
1;
11
05
1*
1(
10
b1110011 !
b1110011 '
04
1"
#110
0"
#115
1+
0&
0:
09
0;
07
13
0-
0*
0)
0(
06
12
b111001 !
b111001 '
0,
1"
#120
0"
#125
1-
0/
15
0+
1,
0.
14
b1011100 !
b1011100 '
08
1"
#130
0"
#135
17
01
1/
0-
16
00
1.
b101110 !
b101110 '
0,
1"
