Verilog_Implementation/Implementation_of_Multi_Step_MLD/full_adder.v
module full_adder(sum, carry, in1, in2, in3);
	input in1, in2, in3;
	output sum, carry;
	wire t0, t1, t2;

	xor G1(sum, in1, in2, in3);
	and G2(t0, in1, in2);
	and G3(t1, in2, in3);
	and G4(t2, in1, in3);
	or G5(carry, t0, t1, t2);
endmodule

Verilog_Implementation/Implementation_of_Multi_Step_MLD/majority_gate_6_input.v
module majority_gate_6_input(out, in1, in2, in3, in4, in5, in6);
	input in1, in2, in3, in4, in5, in6;
	output out;
	wire S1, S2, S3;
	wire C1, C2, C3;
	wire S1_bar, S2_bar;
	wire C_bar;

	assign out = C_bar;

	full_adder FA1(S1, C1, in1, in2, in3);
	full_adder FA2(S2, C2, in4, in5, in6);
	full_adder FA3(S1_bar, C3, S1, S2, 1'b0);
	full_adder FA4(S2_bar, C_bar, C1, C2, C3);
endmodule

Verilog_Implementation/Implementation_of_Multi_Step_MLD/majority_gate_6_input_test_bench.v
module majority_gate_6_input_test_bench;
	reg in1, in2, in3, in4, in5, in6;
	wire out;

	majority_gate_6_input DUT(out, in1, in2, in3, in4, in5, in6);

	initial begin
		$dumpfile("majority_gate_6_input.vcd");
		$dumpvars(0, majority_gate_6_input_test_bench);
		$monitor("in1 = %b, in2 = %b, in3 = %b, in4 = %b, in5 = %b, in6 = %b, out = %b", in1, in2, in3, in4, in5, in6, out);

		in1 = 1'b0; in2 = 1'b0; in3 = 1'b0; in4 = 1'b0; in5 = 1'b0; in6 = 1'b0;
		#10 in1 = 1'b1;
		#10 in2 = 1'b1;
		#10 in3 = 1'b1;
		#10 in5 = 1'b1;
		#10 in6 = 1'b1;
		#10 in4 = 1'b0;
		#10 in3 = 1'b0; 
		#10 in2 = 1'b0; 
		#10 in1 = 1'b0;
	end
endmodule

Verilog_Implementation/Implementation_of_Multi_Step_MLD/majority_gate_6_input.vcd
$date
	Wed Jan 25 18:46:42 2023
$end
$version
	Icarus Verilog
$end
$timescale
	1s
$end
$scope module majority_gate_6_input_test_bench $end
$var wire 1 ! out $end
$var reg 1 " in1 $end
$var reg 1 # in2 $end
$var reg 1 $ in3 $end
$var reg 1 % in4 $end
$var reg 1 & in5 $end
$var reg 1 ' in6 $end
$scope module DUT $end
$var wire 1 " in1 $end
$var wire 1 # in2 $end
$var wire 1 $ in3 $end
$var wire 1 % in4 $end
$var wire 1 & in5 $end
$var wire 1 ' in6 $end
$var wire 1 ! out $end
$var wire 1 ( S2_bar $end
$var wire 1 ) S2 $end
$var wire 1 * S1_bar $end
$var wire 1 + S1 $end
$var wire 1 , C_bar $end
$var wire 1 - C3 $end
$var wire 1 . C2 $end
$var wire 1 / C1 $end
$scope module FA1 $end
$var wire 1 / carry $end
$var wire 1 " in1 $end
$var wire 1 # in2 $end
$var wire 1 $ in3 $end
$var wire 1 + sum $end
$var wire 1 0 t0 $end
$var wire 1 1 t1 $end
$var wire 1 2 t2 $end
$upscope $end
$scope module FA2 $end
$var wire 1 . carry $end
$var wire 1 % in1 $end
$var wire 1 & in2 $end
$var wire 1 ' in3 $end
$var wire 1 ) sum $end
$var wire 1 3 t0 $end
$var wire 1 4 t1 $end
$var wire 1 5 t2 $end
$upscope $end
$scope module FA3 $end
$var wire 1 - carry $end
$var wire 1 + in1 $end
$var wire 1 ) in2 $end
$var wire 1 6 in3 $end
$var wire 1 * sum $end
$var wire 1 7 t0 $end
$var wire 1 8 t1 $end
$var wire 1 9 t2 $end
$upscope $end
$scope module FA4 $end
$var wire 1 , carry $end
$var wire 1 / in1 $end
$var wire 1 . in2 $end
$var wire 1 - in3 $end
$var wire 1 ( sum $end
$var wire 1 : t0 $end
$var wire 1 ; t1 $end
$var wire 1 < t2 $end
$upscope $end
$upscope $end
$upscope $end
$enddefinitions $end
#0
$dumpvars
0<
0;
0:
09
08
07
06
05
04
03
02
01
00
0/
0.
0-
0,
0+
0*
0)
0(
0'
0&
0%
0$
0#
0"
0!
$end
#10
1*
1+
1"
#20
1(
0*
1/
0+
10
1#
#30
1*
1+
11
12
1$
#40
1!
1,
0(
1<
1-
0*
17
1)
1&
#50
0<
0-
0(
1:
0;
1*
07
1.
0)
14
1'
#70
0*
0+
01
02
0$
#80
0!
0,
1(
0:
1*
0/
1+
00
0#
#90
0*
0+
0"
