Verilog_Implementation/Implementation_of_Multi_Step_MLD/full_adder.v
module full_adder(sum, carry, in1, in2, in3);
	input in1, in2, in3;
	output sum, carry;
	wire t0, t1, t2;

	xor G1(sum, in1, in2, in3);
	and G2(t0, in1, in2);
	and G3(t1, in2, in3);
	and G4(t2, in1, in3);
	or G5(carry, t0, t1, t2);
endmodule

Verilog_Implementation/Implementation_of_Multi_Step_MLD/majority_gate_6_input.v
module majority_gate_6_input(out, in1, in2, in3, in4, in5, in6);
	input in1, in2, in3, in4, in5, in6;
	output out;
	wire S1, S2, S3;
	wire C1, C2, C3;
	wire S1_bar, S2_bar;
	wire C_bar;

	assign out = C_bar;

	full_adder FA1(S1, C1, in1, in2, in3);
	full_adder FA2(S2, C2, in4, in5, in6);
	full_adder FA3(S1_bar, C3, S1, S2, 1'b0);
	full_adder FA4(S2_bar, C_bar, C1, C2, C3);
endmodule

Verilog_Implementation/Implementation_of_7_4_MLD/Type_I_MLD/d_flip_flop.v
module d_flip_flop(reset, clk, D, Q);
	input reset, clk, D;
	output reg Q;

	always @(posedge clk) begin
		if (reset)
			Q <= 0;
		else
			Q <= D;
	end
endmodule

Verilog_Implementation/Implementation_of_Multi_Step_MLD/Multi_Step_MLD_decoder.v
module Multi_Step_MLD_decoder(clk, reset, load, received_bit_stream, decoded_vector);
	input clk, reset, load;
	input received_bit_stream;
	output[0:14] decoded_vector;
	reg w0;
	reg A11, A12, A13, A14, A15, A16;
	reg A21, A22, A23, A24, A25, A26;
	reg A31, A32, A33, A34, A35, A36;
	reg A41, A42, A43, A44, A45, A46;
	reg A51, A52, A53, A54, A55, A56;
	reg A61, A62, A63, A64, A65, A66;
	wire M1, M2, M3, M4, M5, M6;
	wire error_value;

	d_flip_flop FF1(reset, clk, w0, decoded_vector[0]);
	d_flip_flop FF2(reset, clk, decoded_vector[0], decoded_vector[1]);
	d_flip_flop FF3(reset, clk, decoded_vector[1], decoded_vector[2]);
	d_flip_flop FF4(reset, clk, decoded_vector[2], decoded_vector[3]);
	d_flip_flop FF5(reset, clk, decoded_vector[3], decoded_vector[4]);
	d_flip_flop FF6(reset, clk, decoded_vector[4], decoded_vector[5]);
	d_flip_flop FF7(reset, clk, decoded_vector[5], decoded_vector[6]);
	d_flip_flop FF8(reset, clk, decoded_vector[6], decoded_vector[7]);
	d_flip_flop FF9(reset, clk, decoded_vector[7], decoded_vector[8]);
	d_flip_flop FF10(reset, clk, decoded_vector[8], decoded_vector[9]);
	d_flip_flop FF11(reset, clk, decoded_vector[9], decoded_vector[10]);
	d_flip_flop FF12(reset, clk, decoded_vector[10], decoded_vector[11]);
	d_flip_flop FF13(reset, clk, decoded_vector[11], decoded_vector[12]);
	d_flip_flop FF14(reset, clk, decoded_vector[12], decoded_vector[13]);
	d_flip_flop FF15(reset, clk, decoded_vector[13], decoded_vector[14]);
	majority_gate_6_input MG1(M1, A11, A12, A13, A14, A15, A16);
	majority_gate_6_input MG2(M2, A21, A22, A23, A24, A25, A26);
	majority_gate_6_input MG3(M3, A31, A32, A33, A34, A35, A36);
	majority_gate_6_input MG4(M4, A41, A42, A43, A44, A45, A46);
	majority_gate_6_input MG5(M5, A51, A52, A53, A54, A55, A56);
	majority_gate_6_input MG6(M6, A61, A62, A63, A64, A65, A66);
	majority_gate_6_input MG7(error_value, M1, M2, M3, M4, M5, M6);

	always @(*) begin
		if (load) begin
			w0 = received_bit_stream;
		end
		else begin
			w0 = decoded_vector[14] ^ error_value;
		end

		A11 = decoded_vector[4] ^ decoded_vector[10] ^ decoded_vector[13] ^ decoded_vector[14];
		A12 = decoded_vector[7] ^ decoded_vector[12] ^ decoded_vector[13] ^ decoded_vector[14];
		A13 = decoded_vector[9] ^ decoded_vector[11] ^ decoded_vector[13] ^ decoded_vector[14];
		A14 = decoded_vector[0] ^ decoded_vector[8] ^ decoded_vector[13] ^ decoded_vector[14];
		A15 = decoded_vector[1] ^ decoded_vector[5] ^ decoded_vector[13] ^ decoded_vector[14];
		A16 = decoded_vector[3] ^ decoded_vector[6] ^ decoded_vector[13] ^ decoded_vector[14];

                A21 = decoded_vector[0] ^ decoded_vector[10] ^ decoded_vector[12] ^ decoded_vector[14];
                A22 = decoded_vector[3] ^ decoded_vector[11] ^ decoded_vector[12] ^ decoded_vector[14];
                A23 = decoded_vector[7] ^ decoded_vector[13] ^ decoded_vector[12] ^ decoded_vector[14];
                A24 = decoded_vector[1] ^ decoded_vector[2] ^ decoded_vector[12] ^ decoded_vector[14];
                A25 = decoded_vector[4] ^ decoded_vector[8] ^ decoded_vector[12] ^ decoded_vector[14];
                A26 = decoded_vector[6] ^ decoded_vector[9] ^ decoded_vector[12] ^ decoded_vector[14];

                A31 = decoded_vector[3] ^ decoded_vector[12] ^ decoded_vector[11] ^ decoded_vector[14];
                A32 = decoded_vector[9] ^ decoded_vector[13] ^ decoded_vector[11] ^ decoded_vector[14];
                A33 = decoded_vector[0] ^ decoded_vector[5] ^ decoded_vector[11] ^ decoded_vector[14];
                A34 = decoded_vector[1] ^ decoded_vector[8] ^ decoded_vector[11] ^ decoded_vector[14];
                A35 = decoded_vector[2] ^ decoded_vector[4] ^ decoded_vector[11] ^ decoded_vector[14];
                A36 = decoded_vector[6] ^ decoded_vector[7] ^ decoded_vector[11] ^ decoded_vector[14];

                A41 = decoded_vector[0] ^ decoded_vector[12] ^ decoded_vector[10] ^ decoded_vector[14];
                A42 = decoded_vector[4] ^ decoded_vector[13] ^ decoded_vector[10] ^ decoded_vector[14];
                A43 = decoded_vector[1] ^ decoded_vector[6] ^ decoded_vector[10] ^ decoded_vector[14];
                A44 = decoded_vector[3] ^ decoded_vector[5] ^ decoded_vector[10] ^ decoded_vector[14];
                A45 = decoded_vector[7] ^ decoded_vector[8] ^ decoded_vector[10] ^ decoded_vector[14];
                A46 = decoded_vector[2] ^ decoded_vector[9] ^ decoded_vector[10] ^ decoded_vector[14];

                A51 = decoded_vector[0] ^ decoded_vector[11] ^ decoded_vector[5] ^ decoded_vector[14];
                A52 = decoded_vector[1] ^ decoded_vector[13] ^ decoded_vector[5] ^ decoded_vector[14];
                A53 = decoded_vector[3] ^ decoded_vector[10] ^ decoded_vector[5] ^ decoded_vector[14];
                A54 = decoded_vector[4] ^ decoded_vector[6] ^ decoded_vector[5] ^ decoded_vector[14];
                A55 = decoded_vector[2] ^ decoded_vector[7] ^ decoded_vector[5] ^ decoded_vector[14];
                A56 = decoded_vector[8] ^ decoded_vector[9] ^ decoded_vector[5] ^ decoded_vector[14];

                A61 = decoded_vector[1] ^ decoded_vector[12] ^ decoded_vector[2] ^ decoded_vector[14];
                A62 = decoded_vector[4] ^ decoded_vector[11] ^ decoded_vector[2] ^ decoded_vector[14];
                A63 = decoded_vector[0] ^ decoded_vector[6] ^ decoded_vector[2] ^ decoded_vector[14];
                A64 = decoded_vector[3] ^ decoded_vector[8] ^ decoded_vector[2] ^ decoded_vector[14];
                A65 = decoded_vector[5] ^ decoded_vector[7] ^ decoded_vector[2] ^ decoded_vector[14];
                A66 = decoded_vector[9] ^ decoded_vector[10] ^ decoded_vector[2] ^ decoded_vector[14];

	end
endmodule

Verilog_Implementation/Implementation_of_Multi_Step_MLD/Multi_Step_MLD_decoder_test_bench.v
module Multi_Step_MLD_decoder_test_bench;
	reg clk, reset, load;
	reg received_bit_stream;
	wire[0:14] decoded_vector;
	
	Multi_Step_MLD_decoder DUT(clk, reset, load, received_bit_stream, decoded_vector);

	initial clk = 1'b0;
	always #5 clk = ~clk;

	initial begin
		$dumpfile("Multi_Step_MLD_decoder.vcd");
		$dumpvars(0, Multi_Step_MLD_decoder_test_bench);
		$monitor("Decoded Vector: %b %b %b %b %b %b %b %b %b %b %b %b %b %b %b, Error Value: %b", decoded_vector[0], decoded_vector[1], decoded_vector[2], decoded_vector[3], decoded_vector[4], decoded_vector[5], decoded_vector[6], decoded_vector[7], decoded_vector[8], decoded_vector[9], decoded_vector[10], decoded_vector[11], decoded_vector[12], decoded_vector[13], decoded_vector[14], DUT.error_value);
		#2 load = 1'b1;
		received_bit_stream = 1'b0;
		#10 received_bit_stream = 1'b1;
		#10 received_bit_stream = 1'b1;
		#10 received_bit_stream = 1'b0;
		#10 received_bit_stream = 1'b0;
		#10 received_bit_stream = 1'b1;
		#10 received_bit_stream = 1'b1;
		#10 received_bit_stream = 1'b0;
		#10 received_bit_stream = 1'b1;
		#10 received_bit_stream = 1'b1;
		#10 received_bit_stream = 1'b1;
		#10 received_bit_stream = 1'b0;
		#10 received_bit_stream = 1'b1;
		#10 received_bit_stream = 1'b0;
		#10 received_bit_stream = 1'b1;
		#10 load = 1'b0;
		#148 $finish;
	end	
endmodule

Verilog_Implementation/Implementation_of_Multi_Step_MLD/Multi_Step_MLD_decoder.vcd
$date
	Wed Jan 25 18:55:26 2023
$end
$version
	Icarus Verilog
$end
$timescale
	1s
$end
$scope module Multi_Step_MLD_decoder_test_bench $end
$var wire 15 ! decoded_vector [0:14] $end
$var reg 1 " clk $end
$var reg 1 # load $end
$var reg 1 $ received_bit_stream $end
$var reg 1 % reset $end
$scope module DUT $end
$var wire 1 " clk $end
$var wire 1 # load $end
$var wire 1 $ received_bit_stream $end
$var wire 1 % reset $end
$var wire 1 & error_value $end
$var wire 15 ' decoded_vector [0:14] $end
$var wire 1 ( M6 $end
$var wire 1 ) M5 $end
$var wire 1 * M4 $end
$var wire 1 + M3 $end
$var wire 1 , M2 $end
$var wire 1 - M1 $end
$var reg 1 . A11 $end
$var reg 1 / A12 $end
$var reg 1 0 A13 $end
$var reg 1 1 A14 $end
$var reg 1 2 A15 $end
$var reg 1 3 A16 $end
$var reg 1 4 A21 $end
$var reg 1 5 A22 $end
$var reg 1 6 A23 $end
$var reg 1 7 A24 $end
$var reg 1 8 A25 $end
$var reg 1 9 A26 $end
$var reg 1 : A31 $end
$var reg 1 ; A32 $end
$var reg 1 < A33 $end
$var reg 1 = A34 $end
$var reg 1 > A35 $end
$var reg 1 ? A36 $end
$var reg 1 @ A41 $end
$var reg 1 A A42 $end
$var reg 1 B A43 $end
$var reg 1 C A44 $end
$var reg 1 D A45 $end
$var reg 1 E A46 $end
$var reg 1 F A51 $end
$var reg 1 G A52 $end
$var reg 1 H A53 $end
$var reg 1 I A54 $end
$var reg 1 J A55 $end
$var reg 1 K A56 $end
$var reg 1 L A61 $end
$var reg 1 M A62 $end
$var reg 1 N A63 $end
$var reg 1 O A64 $end
$var reg 1 P A65 $end
$var reg 1 Q A66 $end
$var reg 1 R w0 $end
$scope module FF1 $end
$var wire 1 R D $end
$var wire 1 " clk $end
$var wire 1 % reset $end
$var reg 1 S Q $end
$upscope $end
$scope module FF10 $end
$var wire 1 T D $end
$var wire 1 " clk $end
$var wire 1 % reset $end
$var reg 1 U Q $end
$upscope $end
$scope module FF11 $end
$var wire 1 V D $end
$var wire 1 " clk $end
$var wire 1 % reset $end
$var reg 1 W Q $end
$upscope $end
$scope module FF12 $end
$var wire 1 X D $end
$var wire 1 " clk $end
$var wire 1 % reset $end
$var reg 1 Y Q $end
$upscope $end
$scope module FF13 $end
$var wire 1 Z D $end
$var wire 1 " clk $end
$var wire 1 % reset $end
$var reg 1 [ Q $end
$upscope $end
$scope module FF14 $end
$var wire 1 \ D $end
$var wire 1 " clk $end
$var wire 1 % reset $end
$var reg 1 ] Q $end
$upscope $end
$scope module FF15 $end
$var wire 1 ^ D $end
$var wire 1 " clk $end
$var wire 1 % reset $end
$var reg 1 _ Q $end
$upscope $end
$scope module FF2 $end
$var wire 1 ` D $end
$var wire 1 " clk $end
$var wire 1 % reset $end
$var reg 1 a Q $end
$upscope $end
$scope module FF3 $end
$var wire 1 b D $end
$var wire 1 " clk $end
$var wire 1 % reset $end
$var reg 1 c Q $end
$upscope $end
$scope module FF4 $end
$var wire 1 d D $end
$var wire 1 " clk $end
$var wire 1 % reset $end
$var reg 1 e Q $end
$upscope $end
$scope module FF5 $end
$var wire 1 f D $end
$var wire 1 " clk $end
$var wire 1 % reset $end
$var reg 1 g Q $end
$upscope $end
$scope module FF6 $end
$var wire 1 h D $end
$var wire 1 " clk $end
$var wire 1 % reset $end
$var reg 1 i Q $end
$upscope $end
$scope module FF7 $end
$var wire 1 j D $end
$var wire 1 " clk $end
$var wire 1 % reset $end
$var reg 1 k Q $end
$upscope $end
$scope module FF8 $end
$var wire 1 l D $end
$var wire 1 " clk $end
$var wire 1 % reset $end
$var reg 1 m Q $end
$upscope $end
$scope module FF9 $end
$var wire 1 n D $end
$var wire 1 " clk $end
$var wire 1 % reset $end
$var reg 1 o Q $end
$upscope $end
$scope module MG1 $end
$var wire 1 . in1 $end
$var wire 1 / in2 $end
$var wire 1 0 in3 $end
$var wire 1 1 in4 $end
$var wire 1 2 in5 $end
$var wire 1 3 in6 $end
$var wire 1 - out $end
$var wire 1 p S2_bar $end
$var wire 1 q S2 $end
$var wire 1 r S1_bar $end
$var wire 1 s S1 $end
$var wire 1 t C_bar $end
$var wire 1 u C3 $end
$var wire 1 v C2 $end
$var wire 1 w C1 $end
$scope module FA1 $end
$var wire 1 w carry $end
$var wire 1 . in1 $end
$var wire 1 / in2 $end
$var wire 1 0 in3 $end
$var wire 1 s sum $end
$var wire 1 x t0 $end
$var wire 1 y t1 $end
$var wire 1 z t2 $end
$upscope $end
$scope module FA2 $end
$var wire 1 v carry $end
$var wire 1 1 in1 $end
$var wire 1 2 in2 $end
$var wire 1 3 in3 $end
$var wire 1 q sum $end
$var wire 1 { t0 $end
$var wire 1 | t1 $end
$var wire 1 } t2 $end
$upscope $end
$scope module FA3 $end
$var wire 1 u carry $end
$var wire 1 s in1 $end
$var wire 1 q in2 $end
$var wire 1 ~ in3 $end
$var wire 1 r sum $end
$var wire 1 !" t0 $end
$var wire 1 "" t1 $end
$var wire 1 #" t2 $end
$upscope $end
$scope module FA4 $end
$var wire 1 t carry $end
$var wire 1 w in1 $end
$var wire 1 v in2 $end
$var wire 1 u in3 $end
$var wire 1 p sum $end
$var wire 1 $" t0 $end
$var wire 1 %" t1 $end
$var wire 1 &" t2 $end
$upscope $end
$upscope $end
$scope module MG2 $end
$var wire 1 4 in1 $end
$var wire 1 5 in2 $end
$var wire 1 6 in3 $end
$var wire 1 7 in4 $end
$var wire 1 8 in5 $end
$var wire 1 9 in6 $end
$var wire 1 , out $end
$var wire 1 '" S2_bar $end
$var wire 1 (" S2 $end
$var wire 1 )" S1_bar $end
$var wire 1 *" S1 $end
$var wire 1 +" C_bar $end
$var wire 1 ," C3 $end
$var wire 1 -" C2 $end
$var wire 1 ." C1 $end
$scope module FA1 $end
$var wire 1 ." carry $end
$var wire 1 4 in1 $end
$var wire 1 5 in2 $end
$var wire 1 6 in3 $end
$var wire 1 *" sum $end
$var wire 1 /" t0 $end
$var wire 1 0" t1 $end
$var wire 1 1" t2 $end
$upscope $end
$scope module FA2 $end
$var wire 1 -" carry $end
$var wire 1 7 in1 $end
$var wire 1 8 in2 $end
$var wire 1 9 in3 $end
$var wire 1 (" sum $end
$var wire 1 2" t0 $end
$var wire 1 3" t1 $end
$var wire 1 4" t2 $end
$upscope $end
$scope module FA3 $end
$var wire 1 ," carry $end
$var wire 1 *" in1 $end
$var wire 1 (" in2 $end
$var wire 1 5" in3 $end
$var wire 1 )" sum $end
$var wire 1 6" t0 $end
$var wire 1 7" t1 $end
$var wire 1 8" t2 $end
$upscope $end
$scope module FA4 $end
$var wire 1 +" carry $end
$var wire 1 ." in1 $end
$var wire 1 -" in2 $end
$var wire 1 ," in3 $end
$var wire 1 '" sum $end
$var wire 1 9" t0 $end
$var wire 1 :" t1 $end
$var wire 1 ;" t2 $end
$upscope $end
$upscope $end
$scope module MG3 $end
$var wire 1 : in1 $end
$var wire 1 ; in2 $end
$var wire 1 < in3 $end
$var wire 1 = in4 $end
$var wire 1 > in5 $end
$var wire 1 ? in6 $end
$var wire 1 + out $end
$var wire 1 <" S2_bar $end
$var wire 1 =" S2 $end
$var wire 1 >" S1_bar $end
$var wire 1 ?" S1 $end
$var wire 1 @" C_bar $end
$var wire 1 A" C3 $end
$var wire 1 B" C2 $end
$var wire 1 C" C1 $end
$scope module FA1 $end
$var wire 1 C" carry $end
$var wire 1 : in1 $end
$var wire 1 ; in2 $end
$var wire 1 < in3 $end
$var wire 1 ?" sum $end
$var wire 1 D" t0 $end
$var wire 1 E" t1 $end
$var wire 1 F" t2 $end
$upscope $end
$scope module FA2 $end
$var wire 1 B" carry $end
$var wire 1 = in1 $end
$var wire 1 > in2 $end
$var wire 1 ? in3 $end
$var wire 1 =" sum $end
$var wire 1 G" t0 $end
$var wire 1 H" t1 $end
$var wire 1 I" t2 $end
$upscope $end
$scope module FA3 $end
$var wire 1 A" carry $end
$var wire 1 ?" in1 $end
$var wire 1 =" in2 $end
$var wire 1 J" in3 $end
$var wire 1 >" sum $end
$var wire 1 K" t0 $end
$var wire 1 L" t1 $end
$var wire 1 M" t2 $end
$upscope $end
$scope module FA4 $end
$var wire 1 @" carry $end
$var wire 1 C" in1 $end
$var wire 1 B" in2 $end
$var wire 1 A" in3 $end
$var wire 1 <" sum $end
$var wire 1 N" t0 $end
$var wire 1 O" t1 $end
$var wire 1 P" t2 $end
$upscope $end
$upscope $end
$scope module MG4 $end
$var wire 1 @ in1 $end
$var wire 1 A in2 $end
$var wire 1 B in3 $end
$var wire 1 C in4 $end
$var wire 1 D in5 $end
$var wire 1 E in6 $end
$var wire 1 * out $end
$var wire 1 Q" S2_bar $end
$var wire 1 R" S2 $end
$var wire 1 S" S1_bar $end
$var wire 1 T" S1 $end
$var wire 1 U" C_bar $end
$var wire 1 V" C3 $end
$var wire 1 W" C2 $end
$var wire 1 X" C1 $end
$scope module FA1 $end
$var wire 1 X" carry $end
$var wire 1 @ in1 $end
$var wire 1 A in2 $end
$var wire 1 B in3 $end
$var wire 1 T" sum $end
$var wire 1 Y" t0 $end
$var wire 1 Z" t1 $end
$var wire 1 [" t2 $end
$upscope $end
$scope module FA2 $end
$var wire 1 W" carry $end
$var wire 1 C in1 $end
$var wire 1 D in2 $end
$var wire 1 E in3 $end
$var wire 1 R" sum $end
$var wire 1 \" t0 $end
$var wire 1 ]" t1 $end
$var wire 1 ^" t2 $end
$upscope $end
$scope module FA3 $end
$var wire 1 V" carry $end
$var wire 1 T" in1 $end
$var wire 1 R" in2 $end
$var wire 1 _" in3 $end
$var wire 1 S" sum $end
$var wire 1 `" t0 $end
$var wire 1 a" t1 $end
$var wire 1 b" t2 $end
$upscope $end
$scope module FA4 $end
$var wire 1 U" carry $end
$var wire 1 X" in1 $end
$var wire 1 W" in2 $end
$var wire 1 V" in3 $end
$var wire 1 Q" sum $end
$var wire 1 c" t0 $end
$var wire 1 d" t1 $end
$var wire 1 e" t2 $end
$upscope $end
$upscope $end
$scope module MG5 $end
$var wire 1 F in1 $end
$var wire 1 G in2 $end
$var wire 1 H in3 $end
$var wire 1 I in4 $end
$var wire 1 J in5 $end
$var wire 1 K in6 $end
$var wire 1 ) out $end
$var wire 1 f" S2_bar $end
$var wire 1 g" S2 $end
$var wire 1 h" S1_bar $end
$var wire 1 i" S1 $end
$var wire 1 j" C_bar $end
$var wire 1 k" C3 $end
$var wire 1 l" C2 $end
$var wire 1 m" C1 $end
$scope module FA1 $end
$var wire 1 m" carry $end
$var wire 1 F in1 $end
$var wire 1 G in2 $end
$var wire 1 H in3 $end
$var wire 1 i" sum $end
$var wire 1 n" t0 $end
$var wire 1 o" t1 $end
$var wire 1 p" t2 $end
$upscope $end
$scope module FA2 $end
$var wire 1 l" carry $end
$var wire 1 I in1 $end
$var wire 1 J in2 $end
$var wire 1 K in3 $end
$var wire 1 g" sum $end
$var wire 1 q" t0 $end
$var wire 1 r" t1 $end
$var wire 1 s" t2 $end
$upscope $end
$scope module FA3 $end
$var wire 1 k" carry $end
$var wire 1 i" in1 $end
$var wire 1 g" in2 $end
$var wire 1 t" in3 $end
$var wire 1 h" sum $end
$var wire 1 u" t0 $end
$var wire 1 v" t1 $end
$var wire 1 w" t2 $end
$upscope $end
$scope module FA4 $end
$var wire 1 j" carry $end
$var wire 1 m" in1 $end
$var wire 1 l" in2 $end
$var wire 1 k" in3 $end
$var wire 1 f" sum $end
$var wire 1 x" t0 $end
$var wire 1 y" t1 $end
$var wire 1 z" t2 $end
$upscope $end
$upscope $end
$scope module MG6 $end
$var wire 1 L in1 $end
$var wire 1 M in2 $end
$var wire 1 N in3 $end
$var wire 1 O in4 $end
$var wire 1 P in5 $end
$var wire 1 Q in6 $end
$var wire 1 ( out $end
$var wire 1 {" S2_bar $end
$var wire 1 |" S2 $end
$var wire 1 }" S1_bar $end
$var wire 1 ~" S1 $end
$var wire 1 !# C_bar $end
$var wire 1 "# C3 $end
$var wire 1 ## C2 $end
$var wire 1 $# C1 $end
$scope module FA1 $end
$var wire 1 $# carry $end
$var wire 1 L in1 $end
$var wire 1 M in2 $end
$var wire 1 N in3 $end
$var wire 1 ~" sum $end
$var wire 1 %# t0 $end
$var wire 1 &# t1 $end
$var wire 1 '# t2 $end
$upscope $end
$scope module FA2 $end
$var wire 1 ## carry $end
$var wire 1 O in1 $end
$var wire 1 P in2 $end
$var wire 1 Q in3 $end
$var wire 1 |" sum $end
$var wire 1 (# t0 $end
$var wire 1 )# t1 $end
$var wire 1 *# t2 $end
$upscope $end
$scope module FA3 $end
$var wire 1 "# carry $end
$var wire 1 ~" in1 $end
$var wire 1 |" in2 $end
$var wire 1 +# in3 $end
$var wire 1 }" sum $end
$var wire 1 ,# t0 $end
$var wire 1 -# t1 $end
$var wire 1 .# t2 $end
$upscope $end
$scope module FA4 $end
$var wire 1 !# carry $end
$var wire 1 $# in1 $end
$var wire 1 ## in2 $end
$var wire 1 "# in3 $end
$var wire 1 {" sum $end
$var wire 1 /# t0 $end
$var wire 1 0# t1 $end
$var wire 1 1# t2 $end
$upscope $end
$upscope $end
$scope module MG7 $end
$var wire 1 - in1 $end
$var wire 1 , in2 $end
$var wire 1 + in3 $end
$var wire 1 * in4 $end
$var wire 1 ) in5 $end
$var wire 1 ( in6 $end
$var wire 1 & out $end
$var wire 1 2# S2_bar $end
$var wire 1 3# S2 $end
$var wire 1 4# S1_bar $end
$var wire 1 5# S1 $end
$var wire 1 6# C_bar $end
$var wire 1 7# C3 $end
$var wire 1 8# C2 $end
$var wire 1 9# C1 $end
$scope module FA1 $end
$var wire 1 9# carry $end
$var wire 1 - in1 $end
$var wire 1 , in2 $end
$var wire 1 + in3 $end
$var wire 1 5# sum $end
$var wire 1 :# t0 $end
$var wire 1 ;# t1 $end
$var wire 1 <# t2 $end
$upscope $end
$scope module FA2 $end
$var wire 1 8# carry $end
$var wire 1 * in1 $end
$var wire 1 ) in2 $end
$var wire 1 ( in3 $end
$var wire 1 3# sum $end
$var wire 1 =# t0 $end
$var wire 1 ># t1 $end
$var wire 1 ?# t2 $end
$upscope $end
$scope module FA3 $end
$var wire 1 7# carry $end
$var wire 1 5# in1 $end
$var wire 1 3# in2 $end
$var wire 1 @# in3 $end
$var wire 1 4# sum $end
$var wire 1 A# t0 $end
$var wire 1 B# t1 $end
$var wire 1 C# t2 $end
$upscope $end
$scope module FA4 $end
$var wire 1 6# carry $end
$var wire 1 9# in1 $end
$var wire 1 8# in2 $end
$var wire 1 7# in3 $end
$var wire 1 2# sum $end
$var wire 1 D# t0 $end
$var wire 1 E# t1 $end
$var wire 1 F# t2 $end
$upscope $end
$upscope $end
$upscope $end
$upscope $end
$enddefinitions $end
#0
$dumpvars
xF#
xE#
xD#
0C#
0B#
xA#
0@#
x?#
x>#
x=#
x<#
x;#
x:#
x9#
x8#
x7#
x6#
x5#
x4#
x3#
x2#
x1#
x0#
x/#
0.#
0-#
x,#
0+#
x*#
x)#
x(#
x'#
x&#
x%#
x$#
x##
x"#
x!#
x~"
x}"
x|"
x{"
xz"
xy"
xx"
0w"
0v"
xu"
0t"
xs"
xr"
xq"
xp"
xo"
xn"
xm"
xl"
xk"
xj"
xi"
xh"
xg"
xf"
xe"
xd"
xc"
0b"
0a"
x`"
0_"
x^"
x]"
x\"
x["
xZ"
xY"
xX"
xW"
xV"
xU"
xT"
xS"
xR"
xQ"
xP"
xO"
xN"
0M"
0L"
xK"
0J"
xI"
xH"
xG"
xF"
xE"
xD"
xC"
xB"
xA"
x@"
x?"
x>"
x="
x<"
x;"
x:"
x9"
08"
07"
x6"
05"
x4"
x3"
x2"
x1"
x0"
x/"
x."
x-"
x,"
x+"
x*"
x)"
x("
x'"
x&"
x%"
x$"
0#"
0""
x!"
0~
x}
x|
x{
xz
xy
xx
xw
xv
xu
xt
xs
xr
xq
xp
xo
xn
xm
xl
xk
xj
xi
xh
xg
xf
xe
xd
xc
xb
xa
x`
x_
x^
x]
x\
x[
xZ
xY
xX
xW
xV
xU
xT
xS
xR
xQ
xP
xO
xN
xM
xL
xK
xJ
xI
xH
xG
xF
xE
xD
xC
xB
xA
x@
x?
x>
x=
x<
x;
x:
x9
x8
x7
x6
x5
x4
x3
x2
x1
x0
x/
x.
x-
x,
x+
x*
x)
x(
bx '
x&
x%
x$
x#
0"
bx !
$end
#2
0R
0$
1#
#5
0`
b0xxxxxxxxxxxxxx !
b0xxxxxxxxxxxxxx '
0S
1"
#10
0"
#12
1R
1$
#15
0b
1`
0a
b10xxxxxxxxxxxxx !
b10xxxxxxxxxxxxx '
1S
1"
#20
0"
#25
1b
0d
1a
b110xxxxxxxxxxxx !
b110xxxxxxxxxxxx '
0c
1"
#30
0"
#32
0R
0$
#35
0f
1d
0`
0e
1c
b110xxxxxxxxxxx !
b110xxxxxxxxxxx '
0S
1"
#40
0"
#45
0b
1f
0h
0a
1e
b110xxxxxxxxxx !
b110xxxxxxxxxx '
0g
1"
#50
0"
#52
1R
1$
#55
0j
1h
0d
1`
0i
1g
0c
b100110xxxxxxxxx !
b100110xxxxxxxxx '
1S
1"
#60
0"
#65
1b
0f
1j
0l
1a
0e
1i
b1100110xxxxxxxx !
b1100110xxxxxxxx '
0k
1"
#70
0"
#72
0R
0$
#75
0n
1l
0h
1d
0`
0m
1k
0g
1c
b1100110xxxxxxx !
b1100110xxxxxxx '
0S
1"
#80
0"
#82
1R
1$
#85
1`
0b
1f
0j
1n
0T
1S
0a
1e
0i
1m
b101100110xxxxxx !
b101100110xxxxxx '
0o
1"
#90
0"
#95
0V
1T
0l
1h
0d
1b
0U
1o
0k
1g
0c
b1101100110xxxxx !
b1101100110xxxxx '
1a
1"
#100
0"
#105
1d
0f
1j
0n
1V
0X
1c
0e
1i
0m
1U
b11101100110xxxx !
b11101100110xxxx '
0W
1"
#110
0"
#112
0R
0$
#115
0Z
1X
0T
1l
0h
1f
0`
0Y
1W
0o
1k
0g
1e
b11101100110xxx !
b11101100110xxx '
0S
1"
#120
0"
#122
1R
1$
#125
1`
0b
1h
0j
1n
0V
1Z
0\
1S
0a
1g
0i
1m
0U
1Y
b1011101100110xx !
b1011101100110xx '
0[
1"
#130
0"
#132
0R
0$
#135
0^
1\
0X
1T
0l
1j
0d
1b
0`
0]
1[
0W
1o
0k
1i
0c
1a
b1011101100110x !
b1011101100110x '
0S
1"
#140
0"
#142
1R
1$
#145
02#
0&
06#
0E#
07#
0D#
0F#
08#
04#
0A#
09#
0>#
03#
0=#
0?#
0;#
05#
0:#
0<#
0{"
0(
0!#
1f"
0)
0j"
1Q"
0*
0U"
1<"
0+
0@"
1'"
0,
0+"
0p
0-
0t
00#
0"#
0/#
01#
0y"
0k"
0x"
0z"
0d"
0V"
0c"
0e"
0O"
0A"
0N"
0P"
0:"
0,"
09"
0;"
0%"
0u
0$"
0&"
0##
1}"
0,#
0$#
1l"
1h"
0u"
0m"
1W"
1S"
0`"
0X"
1B"
1>"
0K"
0C"
1-"
1)"
06"
0."
0v
1r
0!"
0w
0)#
0|"
0(#
0*#
0&#
1~"
0%#
0'#
0r"
0g"
0q"
1s"
0o"
1i"
0n"
0p"
0]"
0R"
1\"
0^"
0Z"
1T"
0Y"
0["
0H"
0="
0G"
1I"
0E"
1?"
0D"
0F"
13"
0("
02"
04"
00"
1*"
0/"
01"
0|
1q
0{
0}
0y
0s
0x
0z
1`
0b
1d
0f
1l
0n
1V
0Z
1^
0Q
0P
0O
1N
0M
0L
1K
0J
1I
1H
0G
0F
0E
1D
1C
1B
0A
0@
1?
0>
1=
0<
0;
1:
19
18
07
06
15
04
03
02
11
00
0/
0.
1S
0a
1c
0e
1k
0m
1U
0Y
1]
b101011101100110 !
b101011101100110 '
0_
1"
#150
0"
#152
0R
0#
#155
1{"
1p
1##
1w
1)#
1g"
1q"
1r"
0i"
1]"
0\"
1H"
0I"
0q
1y
1s
1x
1z
0\
1X
0T
1n
0h
1f
0d
1b
0`
1Q
1P
0N
1M
1J
0H
1E
0C
0B
1A
1>
0=
1;
0:
16
05
01
10
1/
1.
1R
1_
0[
1W
0o
1m
0g
1e
0c
1a
b10101110110011 !
b10101110110011 '
0S
1"
#160
0"
#165
12#
18#
1=#
1*
1U"
1)
1j"
0Q"
1e"
0f"
1x"
1V"
1A"
1,"
1'"
0h"
1m"
0S"
1`"
0W"
1X"
0B"
0>"
1K"
0)"
16"
0-"
1v
0w
1|"
1(#
1*#
0~"
0g"
0r"
0s"
1n"
1R"
0]"
1Z"
1Y"
1["
0H"
1="
1("
03"
1{
0z
0x
0y
1`
0b
1d
0f
1h
0j
1T
0V
1Z
0^
1O
0M
0K
1G
1F
0D
1B
1@
0?
0>
1=
1<
0;
09
06
14
12
11
00
0/
1S
0a
1c
0e
1g
0i
1o
0U
1Y
b101010111011001 !
b101010111011001 '
0]
1"
#170
0"
