Verilog_Implementation/Implementation_of_7_4_MLD/Type_I_MLD/d_flip_flop.v
module d_flip_flop(reset, clk, D, Q);
	input reset, clk, D;
	output reg Q;

	always @(posedge clk) begin
		if (reset)
			Q <= 0;
		else
			Q <= D;
	end
endmodule

Verilog_Implementation/Implementation_of_15_7_MLD/MLD_15_7_encoder.v
module MLD_15_7_encoder(clk, reset, parity_vector, information_bit);
	input clk, reset, information_bit;
	output[7:0] parity_vector;
	reg ff1_input, ff2_input, ff3_input, ff4_input, ff5_input, ff6_input, ff7_input, ff8_input;
	wire ff1_output, ff2_output, ff3_output, ff4_output, ff5_output, ff6_output, ff7_output, ff8_output;

	assign parity_vector[0] = ff1_output;
	assign parity_vector[1] = ff2_output;
	assign parity_vector[2] = ff3_output;
	assign parity_vector[3] = ff4_output;
	assign parity_vector[4] = ff5_output;
	assign parity_vector[5] = ff6_output;
	assign parity_vector[6] = ff7_output;
	assign parity_vector[7] = ff8_output;	

	d_flip_flop FF1(reset, clk, ff1_input, ff1_output);
	d_flip_flop FF2(reset, clk, ff2_input, ff2_output);
	d_flip_flop FF3(reset, clk, ff3_input, ff3_output);
	d_flip_flop FF4(reset, clk, ff4_input, ff4_output);
	d_flip_flop FF5(reset, clk, ff5_input, ff5_output);
	d_flip_flop FF6(reset, clk, ff6_input, ff6_output);
	d_flip_flop FF7(reset, clk, ff7_input, ff7_output);
	d_flip_flop FF8(reset, clk, ff8_input, ff8_output);

	always @(*) begin
		ff1_input = ff8_output ^ information_bit;
		ff2_input = ff1_output;
		ff3_input = ff2_output;
		ff4_input = ff3_output;
		ff5_input = ff4_output ^ ff1_input;
		ff6_input = ff5_output;
		ff7_input = ff6_output ^ ff1_input;
		ff8_input = ff7_output ^ ff1_input;
	end
endmodule

Verilog_Implementation/Implementation_of_15_7_MLD/MLD_15_7_encoder_test_bench.v
module MLD_15_7_Encoder_test_bench;
	reg reset, clk, information_bit;
	wire[7:0] parity_vector;

	MLD_15_7_encoder DUT(clk, reset, parity_vector, information_bit);

	initial clk = 0;
	always #5 clk = ~clk;

	initial begin
		$dumpfile("MLD_15_7_encoder.vcd");
		$dumpvars(0, MLD_15_7_Encoder_test_bench);
		$monitor("Parity Bits Generated: %b, %b, %b, %b, %b, %b, %b, %b", parity_vector[0], parity_vector[1], parity_vector[2], parity_vector[3], parity_vector[4], parity_vector[5], parity_vector[6], parity_vector[7]);
		information_bit = 1'b0;
		reset = 1'b1;
		#7 reset = 1'b0;
		information_bit = 1'b0;
		#10 information_bit = 1'b1;
		#10 information_bit = 1'b1;
		#10 information_bit = 1'b0;
		#10 information_bit = 1'b0;
		#10 information_bit = 1'b0;
		#10 information_bit = 1'b0;
		#10 $finish;
	end
endmodule

Verilog_Implementation/Implementation_of_15_7_MLD/MLD_15_7_encoder.vcd
$date
	Sun Jan 22 20:49:48 2023
$end
$version
	Icarus Verilog
$end
$timescale
	1s
$end
$scope module MLD_15_7_Encoder_test_bench $end
$var wire 8 ! parity_vector [7:0] $end
$var reg 1 " clk $end
$var reg 1 # information_bit $end
$var reg 1 $ reset $end
$scope module DUT $end
$var wire 1 " clk $end
$var wire 1 # information_bit $end
$var wire 1 $ reset $end
$var wire 8 % parity_vector [7:0] $end
$var wire 1 & ff8_output $end
$var wire 1 ' ff7_output $end
$var wire 1 ( ff6_output $end
$var wire 1 ) ff5_output $end
$var wire 1 * ff4_output $end
$var wire 1 + ff3_output $end
$var wire 1 , ff2_output $end
$var wire 1 - ff1_output $end
$var reg 1 . ff1_input $end
$var reg 1 / ff2_input $end
$var reg 1 0 ff3_input $end
$var reg 1 1 ff4_input $end
$var reg 1 2 ff5_input $end
$var reg 1 3 ff6_input $end
$var reg 1 4 ff7_input $end
$var reg 1 5 ff8_input $end
$scope module FF1 $end
$var wire 1 . D $end
$var wire 1 " clk $end
$var wire 1 $ reset $end
$var reg 1 - Q $end
$upscope $end
$scope module FF2 $end
$var wire 1 / D $end
$var wire 1 " clk $end
$var wire 1 $ reset $end
$var reg 1 , Q $end
$upscope $end
$scope module FF3 $end
$var wire 1 0 D $end
$var wire 1 " clk $end
$var wire 1 $ reset $end
$var reg 1 + Q $end
$upscope $end
$scope module FF4 $end
$var wire 1 1 D $end
$var wire 1 " clk $end
$var wire 1 $ reset $end
$var reg 1 * Q $end
$upscope $end
$scope module FF5 $end
$var wire 1 2 D $end
$var wire 1 " clk $end
$var wire 1 $ reset $end
$var reg 1 ) Q $end
$upscope $end
$scope module FF6 $end
$var wire 1 3 D $end
$var wire 1 " clk $end
$var wire 1 $ reset $end
$var reg 1 ( Q $end
$upscope $end
$scope module FF7 $end
$var wire 1 4 D $end
$var wire 1 " clk $end
$var wire 1 $ reset $end
$var reg 1 ' Q $end
$upscope $end
$scope module FF8 $end
$var wire 1 5 D $end
$var wire 1 " clk $end
$var wire 1 $ reset $end
$var reg 1 & Q $end
$upscope $end
$upscope $end
$upscope $end
$enddefinitions $end
#0
$dumpvars
x5
x4
x3
x2
x1
x0
x/
x.
x-
x,
x+
x*
x)
x(
x'
x&
bx %
1$
0#
0"
bx !
$end
#5
05
04
03
02
01
00
0/
0.
0-
0,
0+
0*
0)
0(
0'
b0 !
b0 %
0&
1"
#7
0$
#10
0"
#15
1"
#17
15
14
12
1.
1#
#20
0"
#25
04
13
02
1/
0.
1-
1)
1'
b11010001 !
b11010001 %
1&
1"
#30
0"
#35
05
14
03
10
0/
0'
1(
0)
1,
b10100010 !
b10100010 %
0-
1"
#37
15
04
12
1.
0#
#40
0"
#45
14
13
11
00
1/
1-
0,
1+
1)
b10010101 !
b10010101 %
0(
1"
#50
0"
#55
05
04
02
01
10
1'
1(
1*
0+
b11111011 !
b11111011 %
1,
1"
#60
0"
#65
14
03
11
0.
1+
0*
0)
0'
b100111 !
b100111 %
0&
1"
#70
0"
#75
15
04
12
0/
1'
0(
1*
b1001110 !
b1001110 %
0-
1"
