Verilog_Implementation/Implementation_of_15_7_MLD/Majority_Gate_4_input.v
module majority_gate_4_input(out, A, B, C, D);
	input A, B, C, D;
	output out;
	wire w0, w1, w2, w3;
	
	and G1(w0, A, B, C);
	and G2(w1, A, C, D);
	and G3(w2, A, B, D);
	and G4(w3, B, C, D);
	or G5(out, w0, w1, w2, w3);
endmodule

Verilog_Implementation/Implementation_of_7_4_MLD/Type_I_MLD/d_flip_flop.v
module d_flip_flop(reset, clk, D, Q);
	input reset, clk, D;
	output reg Q;

	always @(posedge clk) begin
		if (reset)
			Q <= 0;
		else
			Q <= D;
	end
endmodule

Verilog_Implementation/Implementation_of_15_7_MLD/Type_II_MLD/MLD_15_7_decoder.v
module MLD_15_7_decoder(clk, reset, load, received_bit_stream, decoded_vector);
	input clk, reset, load;
	input received_bit_stream;
	output[0:14] decoded_vector;
	reg w0;
	reg parity_check_sum_1, parity_check_sum_2, parity_check_sum_3, parity_check_sum_4;
	wire error_value;

	d_flip_flop FF1(reset, clk, w0, decoded_vector[0]);
	d_flip_flop FF2(reset, clk, decoded_vector[0], decoded_vector[1]);
	d_flip_flop FF3(reset, clk, decoded_vector[1], decoded_vector[2]);
	d_flip_flop FF4(reset, clk, decoded_vector[2], decoded_vector[3]);
	d_flip_flop FF5(reset, clk, decoded_vector[3], decoded_vector[4]);
	d_flip_flop FF6(reset, clk, decoded_vector[4], decoded_vector[5]);
	d_flip_flop FF7(reset, clk, decoded_vector[5], decoded_vector[6]);
	d_flip_flop FF8(reset, clk, decoded_vector[6], decoded_vector[7]);
	d_flip_flop FF9(reset, clk, decoded_vector[7], decoded_vector[8]);
	d_flip_flop FF10(reset, clk, decoded_vector[8], decoded_vector[9]);
	d_flip_flop FF11(reset, clk, decoded_vector[9], decoded_vector[10]);
	d_flip_flop FF12(reset, clk, decoded_vector[10], decoded_vector[11]);
	d_flip_flop FF13(reset, clk, decoded_vector[11], decoded_vector[12]);
	d_flip_flop FF14(reset, clk, decoded_vector[12], decoded_vector[13]);
	d_flip_flop FF15(reset, clk, decoded_vector[13], decoded_vector[14]);
	majority_gate_4_input M(error_value, parity_check_sum_1, parity_check_sum_2, parity_check_sum_3, parity_check_sum_4);

	always @(*) begin
		if (load) begin
			w0 = received_bit_stream;
		end
		else begin
			w0 = decoded_vector[14] ^ error_value;
		end
		parity_check_sum_1 = decoded_vector[3] ^ decoded_vector[11] ^ decoded_vector[12] ^ decoded_vector[14];
		parity_check_sum_2 = decoded_vector[1] ^ decoded_vector[5] ^ decoded_vector[13] ^ decoded_vector[14];
		parity_check_sum_3 = decoded_vector[0] ^ decoded_vector[2] ^ decoded_vector[6] ^ decoded_vector[14];
		parity_check_sum_4 = decoded_vector[7] ^ decoded_vector[8] ^ decoded_vector[10] ^ decoded_vector[14];
	end
endmodule

Verilog_Implementation/Implementation_of_15_7_MLD/Type_II_MLD/MLD_15_7_decoder_test_bench.v
module MLD_15_7_decoder_test_bench;
	reg clk, reset, load;
	reg received_bit_stream;
	wire[0:14] decoded_vector;
	
	MLD_15_7_decoder DUT(clk, reset, load, received_bit_stream, decoded_vector);

	initial clk = 1'b0;
	always #5 clk = ~clk;

	initial begin
		$dumpfile("MLD_15_7_decoder.vcd");
		$dumpvars(0, MLD_15_7_decoder_test_bench);
		$monitor("Decoded Vector: %b %b %b %b %b %b %b %b %b %b %b %b %b %b %b, Error Value: %b", decoded_vector[0], decoded_vector[1], decoded_vector[2], decoded_vector[3], decoded_vector[4], decoded_vector[5], decoded_vector[6], decoded_vector[7], decoded_vector[8], decoded_vector[9], decoded_vector[10], decoded_vector[11], decoded_vector[12], decoded_vector[13], decoded_vector[14], DUT.error_value);
		#2 load = 1'b1;
		received_bit_stream = 1'b1;
		#10 received_bit_stream = 1'b0;
		#10 received_bit_stream = 1'b0;
		#10 received_bit_stream = 1'b0;
		#10 received_bit_stream = 1'b1;
		#10 received_bit_stream = 1'b0;
		#10 received_bit_stream = 1'b0;
		#10 received_bit_stream = 1'b1;
		#10 received_bit_stream = 1'b1;
		#10 received_bit_stream = 1'b1;
		#10 received_bit_stream = 1'b0;
		#10 received_bit_stream = 1'b1;
		#10 received_bit_stream = 1'b0;
		#10 received_bit_stream = 1'b1;
		#10 received_bit_stream = 1'b0;
		#10 load = 1'b0;
		#148 $finish;
	end	
endmodule

Verilog_Implementation/Implementation_of_15_7_MLD/MLD_15_7_decoder.vcd
$date
	Wed Jan 25 00:43:01 2023
$end
$version
	Icarus Verilog
$end
$timescale
	1s
$end
$scope module MLD_15_7_decoder_test_bench $end
$var wire 15 ! decoded_vector [0:14] $end
$var reg 1 " clk $end
$var reg 1 # load $end
$var reg 1 $ received_bit_stream $end
$var reg 1 % reset $end
$scope module DUT $end
$var wire 1 " clk $end
$var wire 1 # load $end
$var wire 1 $ received_bit_stream $end
$var wire 1 % reset $end
$var wire 1 & error_value $end
$var wire 15 ' decoded_vector [0:14] $end
$var reg 1 ( parity_check_sum_1 $end
$var reg 1 ) parity_check_sum_2 $end
$var reg 1 * parity_check_sum_3 $end
$var reg 1 + parity_check_sum_4 $end
$var reg 1 , w0 $end
$scope module FF1 $end
$var wire 1 , D $end
$var wire 1 " clk $end
$var wire 1 % reset $end
$var reg 1 - Q $end
$upscope $end
$scope module FF10 $end
$var wire 1 . D $end
$var wire 1 " clk $end
$var wire 1 % reset $end
$var reg 1 / Q $end
$upscope $end
$scope module FF11 $end
$var wire 1 0 D $end
$var wire 1 " clk $end
$var wire 1 % reset $end
$var reg 1 1 Q $end
$upscope $end
$scope module FF12 $end
$var wire 1 2 D $end
$var wire 1 " clk $end
$var wire 1 % reset $end
$var reg 1 3 Q $end
$upscope $end
$scope module FF13 $end
$var wire 1 4 D $end
$var wire 1 " clk $end
$var wire 1 % reset $end
$var reg 1 5 Q $end
$upscope $end
$scope module FF14 $end
$var wire 1 6 D $end
$var wire 1 " clk $end
$var wire 1 % reset $end
$var reg 1 7 Q $end
$upscope $end
$scope module FF15 $end
$var wire 1 8 D $end
$var wire 1 " clk $end
$var wire 1 % reset $end
$var reg 1 9 Q $end
$upscope $end
$scope module FF2 $end
$var wire 1 : D $end
$var wire 1 " clk $end
$var wire 1 % reset $end
$var reg 1 ; Q $end
$upscope $end
$scope module FF3 $end
$var wire 1 < D $end
$var wire 1 " clk $end
$var wire 1 % reset $end
$var reg 1 = Q $end
$upscope $end
$scope module FF4 $end
$var wire 1 > D $end
$var wire 1 " clk $end
$var wire 1 % reset $end
$var reg 1 ? Q $end
$upscope $end
$scope module FF5 $end
$var wire 1 @ D $end
$var wire 1 " clk $end
$var wire 1 % reset $end
$var reg 1 A Q $end
$upscope $end
$scope module FF6 $end
$var wire 1 B D $end
$var wire 1 " clk $end
$var wire 1 % reset $end
$var reg 1 C Q $end
$upscope $end
$scope module FF7 $end
$var wire 1 D D $end
$var wire 1 " clk $end
$var wire 1 % reset $end
$var reg 1 E Q $end
$upscope $end
$scope module FF8 $end
$var wire 1 F D $end
$var wire 1 " clk $end
$var wire 1 % reset $end
$var reg 1 G Q $end
$upscope $end
$scope module FF9 $end
$var wire 1 H D $end
$var wire 1 " clk $end
$var wire 1 % reset $end
$var reg 1 I Q $end
$upscope $end
$scope module M $end
$var wire 1 ( A $end
$var wire 1 ) B $end
$var wire 1 * C $end
$var wire 1 + D $end
$var wire 1 & out $end
$var wire 1 J w0 $end
$var wire 1 K w1 $end
$var wire 1 L w2 $end
$var wire 1 M w3 $end
$upscope $end
$upscope $end
$upscope $end
$enddefinitions $end
#0
$dumpvars
xM
xL
xK
xJ
xI
xH
xG
xF
xE
xD
xC
xB
xA
x@
x?
x>
x=
x<
x;
x:
x9
x8
x7
x6
x5
x4
x3
x2
x1
x0
x/
x.
x-
x,
x+
x*
x)
x(
bx '
x&
x%
x$
x#
0"
bx !
$end
#2
1,
1$
1#
#5
1:
b1xxxxxxxxxxxxxx !
b1xxxxxxxxxxxxxx '
1-
1"
#10
0"
#12
0,
0$
#15
1<
0:
1;
b1xxxxxxxxxxxxx !
b1xxxxxxxxxxxxx '
0-
1"
#20
0"
#25
0<
1>
0;
b1xxxxxxxxxxxx !
b1xxxxxxxxxxxx '
1=
1"
#30
0"
#35
1@
0>
1?
b1xxxxxxxxxxx !
b1xxxxxxxxxxx '
0=
1"
#40
0"
#45
0@
1B
0?
b1xxxxxxxxxx !
b1xxxxxxxxxx '
1A
1"
#50
0"
#52
1,
1$
#55
1D
0B
1:
1C
0A
b100001xxxxxxxxx !
b100001xxxxxxxxx '
1-
1"
#60
0"
#62
0,
0$
#65
0:
1<
0D
1F
0-
1;
0C
b100001xxxxxxxx !
b100001xxxxxxxx '
1E
1"
#70
0"
#72
1,
1$
#75
1H
0F
1>
0<
1:
1G
0E
1=
0;
b10100001xxxxxxx !
b10100001xxxxxxx '
1-
1"
#80
0"
#85
1<
0>
1@
0H
1.
1;
0=
1?
0G
b110100001xxxxxx !
b110100001xxxxxx '
1I
1"
#90
0"
#95
10
0.
1B
0@
1>
1/
0I
1A
0?
b1110100001xxxxx !
b1110100001xxxxx '
1=
1"
#100
0"
#102
0,
0$
#105
0:
1@
0B
1D
00
12
0-
1?
0A
1C
0/
b1110100001xxxx !
b1110100001xxxx '
11
1"
#110
0"
#112
1,
1$
#115
14
02
1F
0D
1B
0<
1:
13
01
1E
0C
1A
0;
b101110100001xxx !
b101110100001xxx '
1-
1"
#120
0"
#125
1<
0>
1D
0F
1H
04
16
1;
0=
1C
0E
1G
03
b1101110100001xx !
b1101110100001xx '
15
1"
#130
0"
#132
0,
0$
#135
18
06
1.
0H
1F
0@
1>
0:
17
05
1I
0G
1E
0?
1=
b1101110100001x !
b1101110100001x '
0-
1"
#140
0"
#145
0&
0M
0J
0K
0L
0<
1@
0B
1H
0.
10
08
0+
1*
0)
0(
0;
1?
0A
1G
0I
1/
07
b1101110100001 !
b1101110100001 '
19
1"
#150
0"
#152
1,
0#
#155
12
00
1.
0D
1B
0>
1:
1+
0*
1(
0,
09
11
0/
1I
0C
1A
0=
b100110111010000 !
b100110111010000 '
1-
1"
#160
0"
#165
0:
1<
0@
1D
0F
10
02
14
0+
0-
1;
0?
1C
0E
1/
01
b10011011101000 !
b10011011101000 '
13
1"
#170
0"
#175
16
04
12
0H
1F
0B
1>
0<
1)
15
03
11
0G
1E
0A
1=
b1001101110100 !
b1001101110100 '
0;
1"
#180
0"
#185
0>
1@
0D
1H
0.
14
06
18
1*
0(
0=
1?
0C
1G
0I
13
05
b100110111010 !
b100110111010 '
17
1"
#190
0"
#195
1&
1J
08
16
00
1.
0F
1B
0@
1(
0,
19
07
15
0/
1I
0E
1A
b10011011101 !
b10011011101 '
0?
1"
#200
0"
#205
0&
0J
0B
1D
0H
10
02
18
1+
0*
0)
0(
0,
0A
1C
0G
1/
01
17
b1001101110 !
b1001101110 '
09
1"
#210
0"
#215
04
12
0.
1F
0D
0+
1,
19
03
11
0I
1E
b100110111 !
b100110111 '
0C
1"
#220
0"
#225
1:
0F
1H
00
14
06
1+
1-
0E
1G
0/
13
b100000010011011 !
b100000010011011 '
05
1"
#230
0"
#235
08
16
02
1.
0H
1<
0+
1(
07
15
01
1I
0G
b110000001001101 !
b110000001001101 '
1;
1"
#240
0"
#245
1>
0.
10
04
18
0,
1=
0I
1/
03
17
b111000000100110 !
b111000000100110 '
09
1"
#250
0"
#255
06
12
00
1@
0:
1)
0(
1,
19
05
11
0/
1?
b11100000010011 !
b11100000010011 '
0-
1"
#260
0"
#265
0,
1&
1M
1J
1K
1L
1:
0<
1B
02
14
08
1+
1*
1(
1-
0;
1A
01
13
b101110000001001 !
b101110000001001 '
07
1"
#270
0"
#275
0&
0M
0J
0K
0L
16
04
1D
0>
1<
0:
0+
0*
0)
0(
0,
09
15
03
1C
0=
1;
b10111000000100 !
b10111000000100 '
0-
1"
#280
0"
#285
0<
1>
0@
1F
06
18
0;
1=
0?
1E
05
b1011100000010 !
b1011100000010 '
17
1"
#290
0"
#295
08
1H
0B
1@
0>
1,
19
07
1G
0A
1?
b101110000001 !
b101110000001 '
0=
1"
