Verilog_Implementation/Implementation_of_15_7_MLD/Type_I_MLD/mux_2_1.v
module mux_2_1(in0, in1, out, sel);
	input in0, in1, sel;
	output reg out;

	always @(*) begin
		if (sel)
			out = in1;
		else
			out = in0;
	end
endmodule

Verilog_Implementation/Implementation_of_7_4_MLD/Type_I_MLD/d_flip_flop.v
module d_flip_flop(reset, clk, D, Q);
	input reset, clk, D;
	output reg Q;

	always @(posedge clk) begin
		if (reset)
			Q <= 0;
		else
			Q <= D;
	end
endmodule

Verilog_Implementation/Implementation_of_7_4_MLD/Type_II_MLD/MLD_7_4_encoder.v
module MLD_7_4_encoder(clk, reset, out, information_bit, sel);
	input clk, reset, information_bit, sel;
	output out;
	reg ff1_input, ff2_input, ff3_input, ff4_input;
	wire ff1_output, ff2_output, ff3_output, ff4_output;
	wire gate_input, gate_output;
	wire final_ff_output_after_delay;

	assign gate_input = ff4_output ^ information_bit;	

	d_flip_flop FF1(reset, clk, ff1_input, ff1_output);
	d_flip_flop FF2(reset, clk, ff2_input, ff2_output);
	d_flip_flop FF3(reset, clk, ff3_input, ff3_output);
	d_flip_flop FF4(reset, clk, ff4_input, ff4_output);
	mux_2_1 SWITCH(information_bit, final_ff_output_after_delay, out, sel);
	mux_2_1 GATE(gate_input, 1'b0, gate_output, sel);
	buf #2 G1(final_ff_output_after_delay, ff4_output);

	always @(*) begin
		ff1_input = gate_output;
		ff2_input = ff1_output;
		ff3_input = gate_output ^ ff2_output;
		ff4_input = gate_output ^ ff3_output;
	end
endmodule

Verilog_Implementation/Implementation_of_7_4_MLD/Type_I_MLD/MLD_7_4_encoder_test_bench.v
module MLD_7_4_Encoder_test_bench;
	reg reset, clk, information_bit, sel;
	wire out;

	MLD_7_4_encoder DUT(clk, reset, out, information_bit, sel);

	initial clk = 0;
	always #5 clk = ~clk;

	initial begin
		$dumpfile("MLD_7_4_encoder.vcd");
		$dumpvars(0, MLD_7_4_Encoder_test_bench);
		$monitor($time, ": Bit Sent into the Channel: %b", out);
		information_bit = 1'b0;
		sel = 1'b0;
		reset = 1'b1;
		#7 reset = 1'b0;
		information_bit = 1'b0;
		#10 information_bit = 1'b1;
		#10 information_bit = 1'b1;
		#10 sel = 1'b1;
		information_bit = 1'b0;
		#40 $finish;
	end
endmodule

Verilog_Implementation/Implementation_of_7_4_MLD/Type_I_MLD/MLD_7_4_encoder.vcd
$date
	Tue Jan 24 22:28:12 2023
$end
$version
	Icarus Verilog
$end
$timescale
	1s
$end
$scope module MLD_7_4_Encoder_test_bench $end
$var wire 1 ! out $end
$var reg 1 " clk $end
$var reg 1 # information_bit $end
$var reg 1 $ reset $end
$var reg 1 % sel $end
$scope module DUT $end
$var wire 1 " clk $end
$var wire 1 & final_ff_output_after_delay $end
$var wire 1 ' gate_input $end
$var wire 1 # information_bit $end
$var wire 1 $ reset $end
$var wire 1 % sel $end
$var wire 1 ! out $end
$var wire 1 ( gate_output $end
$var wire 1 ) ff4_output $end
$var wire 1 * ff3_output $end
$var wire 1 + ff2_output $end
$var wire 1 , ff1_output $end
$var reg 1 - ff1_input $end
$var reg 1 . ff2_input $end
$var reg 1 / ff3_input $end
$var reg 1 0 ff4_input $end
$scope module FF1 $end
$var wire 1 - D $end
$var wire 1 " clk $end
$var wire 1 $ reset $end
$var reg 1 , Q $end
$upscope $end
$scope module FF2 $end
$var wire 1 . D $end
$var wire 1 " clk $end
$var wire 1 $ reset $end
$var reg 1 + Q $end
$upscope $end
$scope module FF3 $end
$var wire 1 / D $end
$var wire 1 " clk $end
$var wire 1 $ reset $end
$var reg 1 * Q $end
$upscope $end
$scope module FF4 $end
$var wire 1 0 D $end
$var wire 1 " clk $end
$var wire 1 $ reset $end
$var reg 1 ) Q $end
$upscope $end
$scope module GATE $end
$var wire 1 ' in0 $end
$var wire 1 1 in1 $end
$var wire 1 % sel $end
$var reg 1 ( out $end
$upscope $end
$scope module SWITCH $end
$var wire 1 # in0 $end
$var wire 1 & in1 $end
$var wire 1 % sel $end
$var reg 1 ! out $end
$upscope $end
$upscope $end
$upscope $end
$enddefinitions $end
#0
$dumpvars
01
x0
x/
x.
x-
x,
x+
x*
x)
x(
x'
x&
0%
1$
0#
0"
0!
$end
#5
00
0/
0-
0(
0.
0'
0,
0+
0*
0)
1"
#7
0&
0$
#10
0"
#15
1"
#17
10
1/
1-
1(
1'
1!
1#
#20
0"
#25
0/
0-
0(
10
1.
0'
1,
1*
1)
1"
#27
1&
#30
0"
#35
00
1/
0.
0*
1+
0,
1"
#37
1'
0#
1%
#40
0"
#45
10
0/
0'
0+
1*
0)
1"
#47
0!
0&
#50
0"
#55
1'
00
1)
0*
1"
#57
1!
1&
#60
0"
#65
0'
0)
1"
#67
0!
0&
