Verilog_Implementation/majority_gate_3_input.v
module majority_gate_3_input(M, A, B, C);
	input A, B, C;
	output M;
	wire t0, t1, t2;

	and G1(t0, A, B);
	and G2(t1, B, C);
	and G3(t2, A, C);
	or G4(M, t0, t1, t2);
endmodule

Verilog_Implementation/Implementation_of_7_4_MLD/Type_I_MLD/d_flip_flop.v
module d_flip_flop(reset, clk, D, Q);
	input reset, clk, D;
	output reg Q;

	always @(posedge clk) begin
		if (reset)
			Q <= 0;
		else
			Q <= D;
	end
endmodule

Verilog_Implementation/MLD_7_4_decoder.v
module MLD_7_4_decoder(clk, reset, load, received_vector, decoded_vector);
	input clk, reset, load;
	input[0:6] received_vector;
	output[0:6] decoded_vector;
	reg w0, w1, w2, w3, w4, w5, w6;
	reg parity_check_sum_1, parity_check_sum_2, parity_check_sum_3;
	wire error_value;

	d_flip_flop FF1(reset, clk, w0, decoded_vector[0]);
	d_flip_flop FF2(reset, clk, w1, decoded_vector[1]);
	d_flip_flop FF3(reset, clk, w2, decoded_vector[2]);
	d_flip_flop FF4(reset, clk, w3, decoded_vector[3]);
	d_flip_flop FF5(reset, clk, w4, decoded_vector[4]);
	d_flip_flop FF6(reset, clk, w5, decoded_vector[5]);
	d_flip_flop FF7(reset, clk, w6, decoded_vector[6]);
	majority_gate_3_input M(error_value, parity_check_sum_1, parity_check_sum_2, parity_check_sum_3);

	always @(*) begin
		if (load) begin
			w0 = received_vector[0];
			w1 = received_vector[1];
			w2 = received_vector[2]; 
			w3 = received_vector[3];
			w4 = received_vector[4];
			w5 = received_vector[5];
			w6 = received_vector[6];
		end
		else begin
			w0 = decoded_vector[6] ^ error_value;
			w1 = decoded_vector[0];
			w2 = decoded_vector[1];
			w3 = decoded_vector[2];
			w4 = decoded_vector[3];
			w5 = decoded_vector[4];
			w6 = decoded_vector[5];
		end
		parity_check_sum_1 = decoded_vector[3] ^ decoded_vector[4] ^ decoded_vector[6];
		parity_check_sum_2 = decoded_vector[1] ^ decoded_vector[5] ^ decoded_vector[6];
		parity_check_sum_3 = decoded_vector[0] ^ decoded_vector[2] ^ decoded_vector[6];
	end
endmodule

Verilog_Implementation/Implementation_of_7_4_MLD/MLD_7_4_decoder_test_bench.v
module MLD_7_4_decoder_test_bench;
	reg clk, reset, load;
	reg[0:6] received_vector;
	wire[0:6] decoded_vector;
	
	MLD_7_4_decoder DUT(clk, reset, load, received_vector, decoded_vector);

	initial clk = 1'b0;
	always #5 clk = ~clk;

	initial begin
		$dumpfile("MLD_7_4_decoder.vcd");
		$dumpvars(0, MLD_7_4_decoder_test_bench);
		$monitor("Decoded Vector: %b %b %b %b %b %b %b", decoded_vector[0], decoded_vector[1], decoded_vector[2], decoded_vector[3], decoded_vector[4], decoded_vector[5], decoded_vector[6]);
		#2 load = 1'b1;
		received_vector = 7'b1101110;
		#10 load = 1'b0;
		#68 $finish;
	end	
endmodule

Verilog_Implementation/MLD_7_4_decoder.vcd
$date
	Sun Jan 22 03:26:57 2023
$end
$version
	Icarus Verilog
$end
$timescale
	1s
$end
$scope module MLD_7_4_decoder_test_bench $end
$var wire 7 ! decoded_vector [0:6] $end
$var reg 1 " clk $end
$var reg 1 # load $end
$var reg 7 $ received_vector [0:6] $end
$var reg 1 % reset $end
$scope module DUT $end
$var wire 1 " clk $end
$var wire 1 # load $end
$var wire 7 & received_vector [0:6] $end
$var wire 1 % reset $end
$var wire 1 ' error_value $end
$var wire 7 ( decoded_vector [0:6] $end
$var reg 1 ) parity_check_sum_1 $end
$var reg 1 * parity_check_sum_2 $end
$var reg 1 + parity_check_sum_3 $end
$var reg 1 , w0 $end
$var reg 1 - w1 $end
$var reg 1 . w2 $end
$var reg 1 / w3 $end
$var reg 1 0 w4 $end
$var reg 1 1 w5 $end
$var reg 1 2 w6 $end
$scope module FF1 $end
$var wire 1 , D $end
$var wire 1 " clk $end
$var wire 1 % reset $end
$var reg 1 3 Q $end
$upscope $end
$scope module FF2 $end
$var wire 1 - D $end
$var wire 1 " clk $end
$var wire 1 % reset $end
$var reg 1 4 Q $end
$upscope $end
$scope module FF3 $end
$var wire 1 . D $end
$var wire 1 " clk $end
$var wire 1 % reset $end
$var reg 1 5 Q $end
$upscope $end
$scope module FF4 $end
$var wire 1 / D $end
$var wire 1 " clk $end
$var wire 1 % reset $end
$var reg 1 6 Q $end
$upscope $end
$scope module FF5 $end
$var wire 1 0 D $end
$var wire 1 " clk $end
$var wire 1 % reset $end
$var reg 1 7 Q $end
$upscope $end
$scope module FF6 $end
$var wire 1 1 D $end
$var wire 1 " clk $end
$var wire 1 % reset $end
$var reg 1 8 Q $end
$upscope $end
$scope module FF7 $end
$var wire 1 2 D $end
$var wire 1 " clk $end
$var wire 1 % reset $end
$var reg 1 9 Q $end
$upscope $end
$scope module M $end
$var wire 1 ) A $end
$var wire 1 * B $end
$var wire 1 + C $end
$var wire 1 ' M $end
$var wire 1 : t0 $end
$var wire 1 ; t1 $end
$var wire 1 < t2 $end
$upscope $end
$upscope $end
$upscope $end
$enddefinitions $end
#0
$dumpvars
x<
x;
x:
x9
x8
x7
x6
x5
x4
x3
x2
x1
x0
x/
x.
x-
x,
x+
x*
x)
bx (
x'
bx &
x%
bx $
x#
0"
bx !
$end
#2
02
11
10
1/
0.
1-
1,
b1101110 $
b1101110 &
1#
#5
0'
0;
0:
0<
1+
0*
0)
13
14
05
16
17
18
b1101110 !
b1101110 (
09
1"
#10
0"
#12
12
0/
1.
0,
0#
#15
0+
1*
00
1/
0-
1,
19
06
15
b110111 !
b110111 (
03
1"
#20
0"
#25
1+
0*
01
10
0.
1-
13
04
16
b1011011 !
b1011011 (
07
1"
#30
0"
#35
0+
1)
02
11
0/
1.
08
17
05
b1101101 !
b1101101 (
14
1"
#40
0"
#45
12
00
1/
0,
15
06
18
b1110110 !
b1110110 (
09
1"
#50
0"
#55
1*
0)
01
10
0-
1,
19
07
16
b111011 !
b111011 (
03
1"
#60
0"
#65
0,
1'
1;
1:
1<
1+
1)
02
11
0.
1-
13
04
17
b1011101 !
b1011101 (
08
1"
#70
0"
#75
0'
0;
0:
0<
0+
0*
0)
12
0/
1.
0-
0,
09
18
05
14
b101110 !
b101110 (
03
1"
