Verilog_Implementation/Implementation_of_7_4_MLD/Type_I_MLD/d_flip_flop.v
module d_flip_flop(reset, clk, D, Q);
	input reset, clk, D;
	output reg Q;

	always @(posedge clk) begin
		if (reset)
			Q <= 0;
		else
			Q <= D;
	end
endmodule

Verilog_Implementation/MLD_7_4_encoder.v
module MLD_7_4_encoder(clk, reset, parity_vector, information_bit);
	input clk, reset, information_bit;
	output[3:0] parity_vector;
	reg ff1_input, ff2_input, ff3_input, ff4_input;
	wire ff1_output, ff2_output, ff3_output, ff4_output;

	assign parity_vector[0] = ff1_output;
	assign parity_vector[1] = ff2_output;
	assign parity_vector[2] = ff3_output;
	assign parity_vector[3] = ff4_output;	

	d_flip_flop FF1(reset, clk, ff1_input, ff1_output);
	d_flip_flop FF2(reset, clk, ff2_input, ff2_output);
	d_flip_flop FF3(reset, clk, ff3_input, ff3_output);
	d_flip_flop FF4(reset, clk, ff4_input, ff4_output);

	always @(*) begin
		ff1_input = ff4_output ^ information_bit;
		ff2_input = ff1_output;
		ff3_input = ff1_input ^ ff2_output;
		ff4_input = ff1_input ^ ff3_output;
	end
endmodule

Verilog_Implementation/MLD_7_4_encoder_test_bench.v
module MLD_7_4_Encoder_test_bench;
	reg reset, clk, information_bit;
	wire[3:0] parity_vector;

	MLD_7_4_encoder DUT(clk, reset, parity_vector, information_bit);

	initial clk = 0;
	always #5 clk = ~clk;

	initial begin
		$dumpfile("MLD_7_4_encoder.vcd");
		$dumpvars(0, MLD_7_4_Encoder_test_bench);
		$monitor("Parity Bits Generated: %b, %b, %b, %b", parity_vector[0], parity_vector[1], parity_vector[2], parity_vector[3]);
		information_bit = 1'b0;
		reset = 1'b1;
		#7 reset = 1'b0;
		information_bit = 1'b1;
		#10 information_bit = 1'b0;
		#10 information_bit = 1'b1;
		#10 $finish;
	end
endmodule

Verilog_Implementation/MLD_7_4_encoder.vcd
$date
	Sun Jan 22 01:45:07 2023
$end
$version
	Icarus Verilog
$end
$timescale
	1s
$end
$scope module MLD_7_4_Encoder_test_bench $end
$var wire 4 ! parity_vector [3:0] $end
$var reg 1 " clk $end
$var reg 1 # information_bit $end
$var reg 1 $ reset $end
$scope module DUT $end
$var wire 1 " clk $end
$var wire 1 # information_bit $end
$var wire 1 $ reset $end
$var wire 4 % parity_vector [3:0] $end
$var wire 1 & ff4_output $end
$var wire 1 ' ff3_output $end
$var wire 1 ( ff2_output $end
$var wire 1 ) ff1_output $end
$var reg 1 * ff1_input $end
$var reg 1 + ff2_input $end
$var reg 1 , ff3_input $end
$var reg 1 - ff4_input $end
$scope module FF1 $end
$var wire 1 * D $end
$var wire 1 " clk $end
$var wire 1 $ reset $end
$var reg 1 ) Q $end
$upscope $end
$scope module FF2 $end
$var wire 1 + D $end
$var wire 1 " clk $end
$var wire 1 $ reset $end
$var reg 1 ( Q $end
$upscope $end
$scope module FF3 $end
$var wire 1 , D $end
$var wire 1 " clk $end
$var wire 1 $ reset $end
$var reg 1 ' Q $end
$upscope $end
$scope module FF4 $end
$var wire 1 - D $end
$var wire 1 " clk $end
$var wire 1 $ reset $end
$var reg 1 & Q $end
$upscope $end
$upscope $end
$upscope $end
$enddefinitions $end
#0
$dumpvars
x-
x,
x+
x*
x)
x(
x'
x&
bx %
1$
0#
0"
bx !
$end
#5
0-
0,
0+
0*
0)
0(
0'
b0 !
b0 %
0&
1"
#7
1-
1,
1*
1#
0$
#10
0"
#15
0,
1+
0*
1&
1'
b1101 !
b1101 %
1)
1"
#17
0-
1,
1*
0#
#20
0"
#25
1-
0*
1(
b111 !
b111 %
0&
1"
#27
0-
0,
1*
1#
#30
0"
#35
1-
b11 !
b11 %
0'
1"
